{
  "appPageId" : "43369298-c0db-4ecf-a06a-b46f3ec9629c",
  "componentName" : "siteforce:sldsThreeCol444Layout",
  "dataProviders" : [ ],
  "id" : "798872b6-d902-4d64-b226-a355f2674e4b",
  "label" : "Home",
  "regions" : [ {
    "components" : [ {
      "componentAttributes" : {
        "maxWidth" : 100,
        "overlayColor" : "rgba(0,0,0,0.4)",
        "overlayHoverColor" : "",
        "radius" : 0,
        "showTitle" : false,
        "textAlignment" : "center",
        "textBgColor" : "rgba(0,0,0,0)",
        "textBgHoverColor" : "rgba(0,0,0,0)",
        "textColor" : "",
        "textHoverColor" : "",
        "textPosition" : "center center",
        "title" : "Featured Topics"
      },
      "componentName" : "forceTopic:featuredTopics",
      "id" : "9fc4ec75-40b6-4646-9507-5993816a2137",
      "renderPriority" : "NEUTRAL",
      "renditionMap" : { },
      "type" : "component"
    } ],
    "id" : "31cee6fa-bd6f-4473-9eed-57836b1ed267",
    "regionName" : "header",
    "type" : "region"
  }, {
    "components" : [ {
      "componentAttributes" : {
        "numberOfArticles" : 5,
        "showTitle" : false,
        "title" : "Top Articles",
        "topicList" : [ ]
      },
      "componentName" : "forceCommunity:topArticleList",
      "id" : "a678cae2-f732-4556-b57c-4f0485ffe38d",
      "renderPriority" : "NEUTRAL",
      "renditionMap" : { },
      "type" : "component"
    } ],
    "id" : "6af27c47-5093-4c35-8b9c-1d4f56e0471c",
    "regionName" : "content",
    "type" : "region"
  }, {
    "components" : [ {
      "componentAttributes" : {
        "numberOfArticles" : 5,
        "showTitle" : false,
        "title" : "Top Articles",
        "topicList" : [ ]
      },
      "componentName" : "forceCommunity:topArticleList",
      "id" : "1540824d-f34d-4304-bc97-6c6335dddc75",
      "renderPriority" : "NEUTRAL",
      "renditionMap" : { },
      "type" : "component"
    } ],
    "id" : "dbfa5b1c-197a-4382-9114-e5eca5dbb5de",
    "regionName" : "sidebar",
    "type" : "region"
  }, {
    "components" : [ {
      "componentAttributes" : {
        "numberOfArticles" : 5,
        "showTitle" : false,
        "title" : "Top Articles",
        "topicList" : [ ]
      },
      "componentName" : "forceCommunity:topArticleList",
      "id" : "2374f4bc-c205-4dad-93c1-a7e78cb99ca1",
      "renderPriority" : "NEUTRAL",
      "renditionMap" : { },
      "type" : "component"
    } ],
    "id" : "50e71a9e-b891-4266-a27a-e3852763589b",
    "regionName" : "sidebarAlt",
    "type" : "region"
  }, {
    "id" : "8d22d82d-9e59-439a-a77b-6360070c7bfc",
    "regionName" : "footer",
    "type" : "region"
  }, {
    "components" : [ {
      "componentAttributes" : {
        "customHeadTags" : "",
        "description" : "",
        "title" : "Home"
      },
      "componentName" : "forceCommunity:seoAssistant",
      "id" : "428a15da-f539-4eb5-a1df-cc6252233735",
      "renditionMap" : { },
      "type" : "component"
    } ],
    "id" : "d0762c2e-32c8-4240-ac60-75754fd61939",
    "regionName" : "sfdcHiddenRegion",
    "type" : "region"
  } ],
  "themeLayoutType" : "Home",
  "type" : "view",
  "viewType" : "home"
}